Box2D/Box2D.py
Box2D/_Box2D.cpython-35m-darwin.so
Box2D/__init__.py
Box2D/b2/__init__.py
Box2D_kengz-2.3.3.dist-info/DESCRIPTION.rst
Box2D_kengz-2.3.3.dist-info/METADATA
Box2D_kengz-2.3.3.dist-info/RECORD
Box2D_kengz-2.3.3.dist-info/WHEEL
Box2D_kengz-2.3.3.dist-info/metadata.json
Box2D_kengz-2.3.3.dist-info/top_level.txt
