Metadata-Version: 2.0
Name: Box2D-kengz
Version: 2.3.3
Summary: Python Box2D
Home-page: http://pybox2d.googlecode.com/
Author: Ken Lauer (uploaded by kengz)
Author-email: kengzwl@gmail.com
License: zlib
Platform: UNKNOWN
Classifier: Development Status :: 4 - Beta
Classifier: Intended Audience :: Developers
Classifier: License :: OSI Approved :: zlib/libpng License
Classifier: Operating System :: Microsoft :: Windows
Classifier: Operating System :: MacOS :: MacOS X
Classifier: Operating System :: POSIX
Classifier: Programming Language :: Python
Classifier: Topic :: Software Development :: Libraries :: Python Modules
Classifier: Topic :: Software Development :: Libraries :: pygame
